README.rst
setup.py
imx_nand_tools.egg-info/PKG-INFO
imx_nand_tools.egg-info/SOURCES.txt
imx_nand_tools.egg-info/dependency_links.txt
imx_nand_tools.egg-info/entry_points.txt
imx_nand_tools.egg-info/requires.txt
imx_nand_tools.egg-info/top_level.txt
imxtools/__init__.py
imxtools/fcb.py
imxtools/imx_nand_convert.py
imxtools/imx_nand_info.py