Metadata-Version: 1.2
Name: imx-nand-tools
Version: 1.0.3
Summary: Freescale i.MX NAND reverse tools
Home-page: https://github.com/DigitalSecurity/imx-nand-tools
Author: Damien Cauquil
Author-email: damien.cauquil@digital.security
License: MIT
Keywords: imx freescale tool
Platform: UNKNOWN
Requires-Python: >3.5.2
